Workbook

Sheet HazardData
A1: Physical Risk Source Data
A3: Hazard Baselines
A4: hazard_type | B4: base_frequency | C4: base_intensity | D4: intensity_unit | E4: outage_rate | F4: capacity_derate | G4: efficiency_loss | H4: damage_ratio | I4: confidence_low | J4: confidence_high | K4: source | L4: methodology | M4: climada_events | N4: climada_years | O4: source_url
A5: wildfire | B5: 0.75 | C5: 25 | D5: FWI | E5: 3.4e-05 | F5: 0 | G5: 0 | H5: 0.0001 | I5: 1.7e-05 | J5: 5.1e-05 | K5: CLIMADA WildFire + Korea Forest Service FIRMS (2001-2023) | L5: Outage = Freq x P(outage) x Duration / 8760 | M5: 30 | N5: 40 | O5: https://firms.modaps.eosdis.nasa.gov/
A6: tropical_cyclone | B6: 0 | C6: 0 | D6: m/s | E6: 0 | F6: 0 | G6: 0 | H6: 0 | I6: 0 | J6: 0 | K6: DISABLED (CLIMADA simulation not performed for site) | L6: Not verified for Samcheok | M6: 0 | N6: 0
A7: river_flood | B7: 0 | C7: 0 | D7: m | E7: 0 | F7: 0 | G7: 0 | H7: 0 | I7: 0 | J7: 0 | K7: DISABLED (plant at 10m elevation) | L7: Plant not in flood zone | M7: 0 | N7: 0
A8: coastal_flood | B8: 0 | C8: 0 | D8: m | E8: 0 | F8: 0 | G8: 0 | H8: 0 | I8: 0 | J8: 0 | K8: DISABLED (plant at 10m elevation) | L8: Surge + SLR cannot reach | M8: 0 | N8: 0
A9: drought | B9: 0 | C9: 0 | D9: SPI | E9: 0 | F9: 0 | G9: 0 | H9: 0 | I9: 0 | J9: 0 | K9: OS-Climate PhysRisk API (primary source; CSV fallback disabled) | L9: Use PhysRisk live results only | M9: 0 | N9: 0 | O9: https://physrisk.os-climate.org/
A10: heat_stress | B10: 0 | C10: 0 | D10: C | E10: 0 | F10: 0 | G10: 0 | H10: 0 | I10: 0 | J10: 0 | K10: DISABLED (source not validated for Samcheok) | L10: KMA data referenced but not verified | M10: 0 | N10: 0
A11: sea_level_rise | B11: 0 | C11: 0 | D11: m | E11: 0 | F11: 0 | G11: 0 | H11: 0 | I11: 0 | J11: 0 | K11: NASA/IPCC AR6 SLR projections | L11: Impact via coastal flood frequency | M11: 0 | N11: 0
A13: Climate Factors
A14: scenario | B14: year | C14: wildfire | D14: tropical_cyclone | E14: river_flood | F14: coastal_flood | G14: drought | H14: heat_stress | I14: slr_meters | J14: source
A15: RCP4.5 | B15: 2024 | C15: 1 | D15: 1 | E15: 1 | F15: 1 | G15: 1 | H15: 1 | I15: 0 | J15: Baseline (current climate)
A16: RCP4.5 | B16: 2030 | C16: 1.1 | D16: 1.02 | E16: 1.05 | F16: 1.1 | G16: 1.08 | H16: 1.15 | I16: 0.05 | J16: IPCC AR6 WG1 Table 4.5 + KMA projections
A17: RCP4.5 | B17: 2050 | C17: 1.3 | D17: 1.05 | E17: 1.15 | F17: 1.25 | G17: 1.2 | H17: 1.5 | I17: 0.15 | J17: IPCC AR6 WG1 Table 4.5 + KMA projections
A18: RCP4.5 | B18: 2100 | C18: 1.5 | D18: 1.1 | E18: 1.25 | F18: 1.5 | G18: 1.35 | H18: 2 | I18: 0.4 | J18: IPCC AR6 WG1 Table 4.5 + KMA projections
A19: RCP8.5 | B19: 2024 | C19: 1 | D19: 1 | E19: 1 | F19: 1 | G19: 1 | H19: 1 | I19: 0 | J19: Baseline (current climate)
A20: RCP8.5 | B20: 2030 | C20: 1.15 | D20: 1.03 | E20: 1.08 | F20: 1.15 | G20: 1.12 | H20: 1.2 | I20: 0.07 | J20: IPCC AR6 WG1 Table 4.8 + KMA + WWA
A21: RCP8.5 | B21: 2050 | C21: 2 | D21: 1.1 | E21: 1.3 | F21: 1.5 | G21: 1.4 | H21: 2.5 | I21: 0.25 | J21: IPCC AR6 WG1 Table 4.8 + KMA + WWA
A22: RCP8.5 | B22: 2100 | C22: 4 | D22: 1.2 | E22: 1.5 | F22: 2.5 | G22: 1.8 | H22: 5 | I22: 0.8 | J22: IPCC AR6 WG1 Table 4.8 + KMA + WWA
A23: SSP1-2.6 | B23: 2024 | C23: 1 | D23: 1 | E23: 1 | F23: 1 | G23: 1 | H23: 1 | I23: 0 | J23: Baseline (current climate)
A24: SSP1-2.6 | B24: 2030 | C24: 1.08 | D24: 1.01 | E24: 1.04 | F24: 1.08 | G24: 1.06 | H24: 1.12 | I24: 0.04 | J24: IPCC AR6 WG1 Chapter 4
A25: SSP1-2.6 | B25: 2050 | C25: 1.2 | D25: 1.03 | E25: 1.1 | F25: 1.18 | G25: 1.15 | H25: 1.35 | I25: 0.12 | J25: IPCC AR6 WG1 Chapter 4
A26: SSP1-2.6 | B26: 2100 | C26: 1.3 | D26: 1.05 | E26: 1.15 | F26: 1.3 | G26: 1.25 | H26: 1.5 | I26: 0.3 | J26: IPCC AR6 WG1 Chapter 4
... A34: SSP5-8.5 | B34: 2100 | C34: 4.5 | D34: 1.25 | E34: 1.6 | F34: 2.8 | G34: 2 | H34: 5.5 | I34: 0.9 | J34: IPCC AR6 WG1 Chapter 4
A36: Outage Parameters
A37: asset_type | B37: failure_rate_per_hour | C37: exposure_hours_low | D37: exposure_hours_mid | E37: exposure_hours_high | F37: outage_duration_hours | G37: source_lambda | H37: source_duration | I37: source_url_lambda | J37: source_url_duration
A38: transmission_tower | B38: 0.3 | C38: 1 | D38: 2 | E38: 4 | F38: 24 | G38: Choobineh & Mohagheghi (2015) Table 2 (steel tower 0.2-0.4 range; midpoint) | H38: KFS Forest Fire Statistics 1991-2004 large fire avg 18.5h; point transit sensitivity | I38: https://doi.org/10.1016/j.firesaf.2015.02.006 | J38: https://www.kci.go.kr/kciportal/ci/sereArticleSearch/ciSereArtiView.kci?sereArticleSearchBean.artiId=ART001017472
A39: wooden_pole_line | B39: 0.7 | C39: 1 | D39: 2 | E39: 4 | F39: 24 | G39: Choobineh & Mohagheghi (2015) Table 2 (wooden pole 0.5-1.0 range; midpoint) | H39: KFS Forest Fire Statistics 1991-2004 | I39: https://doi.org/10.1016/j.firesaf.2015.02.006 | J39: https://www.kci.go.kr/kciportal/ci/sereArticleSearch/ciSereArtiView.kci?sereArticleSearchBean.artiId=ART001017472
A40: power_plant | B40: 0.2 | C40: 1 | D40: 2 | E40: 4 | F40: 48 | G40: Choobineh & Mohagheghi (2015) Table 2 (transformer/heavy equipment 0.2-0.4; lower bound) | H40: KFS Forest Fire Statistics 1991-2004 | I40: https://doi.org/10.1016/j.firesaf.2015.02.006 | J40: https://www.kci.go.kr/kciportal/ci/sereArticleSearch/ciSereArtiView.kci?sereArticleSearchBean.artiId=ART001017472
A41: substation | B41: 0.3 | C41: 1 | D41: 2 | E41: 4 | F41: 36 | G41: Choobineh & Mohagheghi (2015) Table 2 (transformer class) | H41: KFS Forest Fire Statistics 1991-2004 | I41: https://doi.org/10.1016/j.firesaf.2015.02.006 | J41: https://www.kci.go.kr/kciportal/ci/sereArticleSearch/ciSereArtiView.kci?sereArticleSearchBean.artiId=ART001017472

Sheet PlantFinance
A1: Plant & Financial Data
A3: Plant Parameters
A4: param_name | B4: value | C4: unit | D4: description
A5: capacity_mw | B5: 2100 | C5: MW | D5: Total capacity (2 units x 1050MW)
A6: capacity_factor | B6: 0.6 | C6: decimal | D6: Base load capacity factor
A7: efficiency | B7: 0.39 | C7: decimal | D7: Supercritical efficiency (3.412/8.8)
A8: fuel_cost_per_mwh | B8: 45 | C8: USD/MWh | D8: Approximate coal cost
A9: variable_opex | B9: 5 | C9: USD/MWh | D9: Variable O&M
A10: fixed_opex_per_kw | B10: 35 | C10: USD/kW-yr | D10: Fixed O&M
A11: variable_opex_per_mwh | B11: 4.5 | C11: USD/MWh | D11: Variable O&M per MWh (alternative)
A12: total_capex_million | B12: 3550 | C12: USD Million | D12: Total project cost (4.9T KRW at 1380 KRW/USD Feb 2026)
A13: construction_years | B13: 5 | C13: years | D13: Construction duration
A14: debt_fraction | B14: 0.8 | C14: decimal | D14: Estimated debt financing share
A15: equity_fraction | B15: 0.2 | C15: decimal | D15: Estimated equity share
A16: debt_interest_rate | B16: 0.05 | C16: decimal | D16: Recent bond yield (6.1%)
A17: debt_schedule_file | B17: debt_repayment_schedule.csv | C17: filename | D17: Custom repayment profile
A18: debt_tenor_years | B18: 20 | C18: years | D18: Loan repayment period (fallback)
A19: risk_free_rate | B19: 0.035 | C19: decimal | D19: Korea 10Y Treasury
A20: market_risk_premium | B20: 0.06 | C20: decimal | D20: Korea Equity Risk Premium
A21: beta | B21: 1.2 | C21: decimal | D21: Utility sector beta (adjusted for coal risk)
A22: corporate_tax_rate | B22: 0.25 | C22: decimal | D22: Korea Corporate Tax Rate (25% effective Jan 2026)
A23: tax_rate | B23: 0.25 | C23: decimal | D23: Korea Corporate Tax Rate (alias)
A24: useful_life | B24: 30 | C24: years | D24: Economic life
A25: operating_years | B25: 40 | C25: years | D25: Total expected operating life
A26: depreciation_years | B26: 20 | C26: years | D26: Depreciation schedule
A27: inflation_rate | B27: 0.02 | C27: decimal | D27: Long-term inflation target
A28: power_price_per_mwh | B28: 80 | C28: USD/MWh | D28: Wholesale electricity price
A29: heat_rate_mmbtu_mwh | B29: 8.8 | C29: MMBtu/MWh | D29: Heat rate for supercritical coal plant
... A32: discount_rate | B32: 0.08 | C32: decimal | D32: Project discount rate for NPV
A34: Financing Parameters
A35: param_name | B35: value | C35: unit | D35: source
A36: spread_slope_bps_per_pct | B36: 50 | C36: bps/% | D36: Model assumption (reduced form credit model)
A37: equity_slope_pct_per_pct | B37: 0.8 | C37: %/% | D37: Model assumption (equity risk premium)
A38: baseline_spread_bps | B38: 150 | C38: bps | D38: Investment grade BBB baseline
A39: risk_free_rate | B39: 0.03 | C39: fraction | D39: Korea 10Y government bond yield 2024
A40: debt_fraction | B40: 0.7 | C40: fraction | D40: Typical project finance leverage
A41: equity_fraction | B41: 0.3 | C41: fraction | D41: Typical project finance equity
A42: baseline_equity_rate | B42: 0.12 | C42: fraction | D42: Korea coal project cost of equity estimate

Sheet TransitionData
A1: Transition Risk Data
A3: Transition Scenarios
A4: scenario | B4: dispatch_penalty | C4: retirement_years | D4: description | E4: source | F4: source_url
A5: baseline | B5: 0 | C5: 40 | D5: No policy intervention | E5: default
A6: moderate_transition | B6: 0 | C6: 35 | D6: Coal phase-out via 11th Basic Plan power mix targets | E6: 11th Basic Plan (Draft 2025) | F6: https://www.motie.go.kr/motie/ms/nt/announce/bbs/bbsView.do?bbs_cd_n=6&bbs_seq_n=68032
A7: aggressive_transition | B7: 0 | C7: 25 | D7: Accelerated coal exit aligned with 2040 carbon neutrality pledge | E7: Presidential pledge 2040 | F7: https://www.reuters.com/business/energy/south-korea-unveils-plan-go-carbon-neutral-by-2050-2020-10-28/
A9: Coal Phase-out
A10: year | B10: capacity_gw | C10: capacity_factor | D10: policy_reference
A11: 2024 | B11: 26.7 | C11: 0.65 | D11: 11th Basic Plan baseline
A12: 2025 | B12: 25 | C12: 0.6 | D12: 11th Basic Plan phase-down start
A13: 2030 | B13: 18 | C13: 0.45 | D13: 11th Basic Plan target
A14: 2035 | B14: 14 | C14: 0.3 | D14: 11th Basic Plan interpolation
A15: 2038 | B15: 12.5 | C15: 0.2 | D15: 11th Basic Plan target
A16: 2040 | B16: 0 | C16: 0 | D16: Presidential pledge 2040 탈석탄
A18: Nuclear Expansion
A19: phase | B19: year | C19: cumulative_capacity_gw | D19: addition_gw | E19: unit_type | F19: source
A20: 0 | B20: 2024 | C20: 24.7 | D20: 0 | E20: existing | F20: 11th Basic Plan baseline
A21: 1 | B21: 2028 | C21: 25.7 | D21: 1 | E21: large_unit | F21: 11th Basic Plan - Shin Hanul 3
A22: 2 | B22: 2032 | C22: 28.1 | D22: 2.4 | E22: large_unit | F22: 11th Basic Plan - Shin Hanul 4
A23: 3 | B23: 2035 | C23: 30.1 | D23: 2 | E23: smr | F23: 11th Basic Plan - SMR deployment
A25: Renewable Targets
A26: year | B26: solar_gw | C26: wind_gw | D26: hydro_gw | E26: grid_stability_gw | F26: battery_gw | G26: source
A27: 2024 | B27: 25 | C27: 1.7 | D27: 6.5 | E27: 0 | F27: 0 | G27: 11th Basic Plan baseline
A28: 2030 | B28: 39 | C28: 10 | D28: 6.5 | E28: 15 | F28: 20 | G28: 11th Basic Plan target
A29: 2035 | B29: 58 | C29: 25 | D29: 6.5 | E29: 18 | F29: 27 | G29: 11th Basic Plan interpolation
A30: 2038 | B30: 77.2 | C30: 40.7 | D30: 6.5 | E30: 21.5 | F30: 35 | G30: 11th Basic Plan target

Sheet CreditData
A1: Credit Rating & Spread Data
A3: Rating Thresholds
A4: metric | B4: threshold_min | C4: threshold_max | D4: rating | E4: source
A5: capacity_mw | B5: 2000 | C5: 999999 | D5: AAA | E5: KIS credit methodology
A6: capacity_mw | B6: 800 | C6: 2000 | D6: AA | E6: KIS credit methodology
A7: capacity_mw | B7: 400 | C7: 800 | D7: A | E7: KIS credit methodology
A8: capacity_mw | B8: 100 | C8: 400 | D8: BBB | E8: KIS credit methodology
A9: capacity_mw | B9: 20 | C9: 100 | D9: BB | E9: KIS credit methodology
A10: capacity_mw | B10: 0 | C10: 20 | D10: B | E10: KIS credit methodology
A11: ebitda_fixed_assets_pct | B11: 15 | C11: 999 | D11: AAA | E11: KIS credit methodology
A12: ebitda_fixed_assets_pct | B12: 11 | C12: 15 | D12: AA | E12: KIS credit methodology
A13: ebitda_fixed_assets_pct | B13: 8 | C13: 11 | D13: A | E13: KIS credit methodology
A14: ebitda_fixed_assets_pct | B14: 4 | C14: 8 | D14: BBB | E14: KIS credit methodology
A15: ebitda_fixed_assets_pct | B15: 1 | C15: 4 | D15: BB | E15: KIS credit methodology
A16: ebitda_fixed_assets_pct | B16: 0 | C16: 1 | D16: B | E16: KIS credit methodology
... A39: dscr | B39: -999 | C39: 0 | D39: D | E39: S&P Project Finance Criteria (2022)
A41: Rating Spreads
A42: rating | B42: spread_bps | C42: source
A43: AAA | B43: 50 | C43: Bloomberg US Corporate Bond Index 2020-2024 average
A44: AA | B44: 100 | C44: Bloomberg US Corporate Bond Index 2020-2024 average
A45: A | B45: 150 | C45: Bloomberg US Corporate Bond Index 2020-2024 average
A46: BBB | B46: 250 | C46: Bloomberg US Corporate Bond Index 2020-2024 average
A47: BB | B47: 400 | C47: Bloomberg US Corporate Bond Index 2020-2024 average
A48: B | B48: 600 | C48: Bloomberg US Corporate Bond Index 2020-2024 average
A49: CCC | B49: 900 | C49: Bloomberg US Corporate Bond Index 2020-2024 average (distressed)
A50: CC | B50: 1500 | C50: Distressed debt trading levels
A51: C | B51: 2500 | C51: Distressed debt deep distress
A52: D | B52: 5000 | C52: Default recovery value pricing

Sheet Calc
A1: CRP CALCULATION (all formulas reference other sheets)
B3: Input Parameter | C3: Value | D3: Unit
A4: P1 | B4: wildfire_frequency | C4: =HazardData!B5 -> 0.75 | D4: events/yr
A5: P2 | B5: climate_factor (RCP4.5 2050) | C5: =HazardData!C17 -> 1.3 | D5: multiplier
A6: P3 | B6: lambda (power_plant) | C6: =HazardData!B40 -> 0.2 | D6: /hour
A7: P4 | B7: exposure_time | C7: =HazardData!D40 -> 2 | D7: hours
A8: P5 | B8: outage_duration | C8: =HazardData!F40 -> 48 | D8: hours
A10: F1 | B10: capacity_mw | C10: =PlantFinance!B5 -> 2100 | D10: MW
A11: F2 | B11: capacity_factor | C11: =PlantFinance!B6 -> 0.6 | D11: fraction
A12: F3 | B12: power_price | C12: =PlantFinance!B28 -> 80 | D12: USD/MWh
A13: F4 | B13: fuel_cost | C13: =PlantFinance!B8 -> 45 | D13: USD/MWh
A14: F5 | B14: fixed_opex | C14: =PlantFinance!B10 -> 35 | D14: USD/kW/yr
A15: F6 | B15: variable_opex | C15: =PlantFinance!B11 -> 4.5 | D15: USD/MWh
A16: F7 | B16: capex_total | C16: =PlantFinance!B12 -> 3550 | D16: M USD
A17: F8 | B17: debt_fraction | C17: =PlantFinance!B14 -> 0.8 | D17: fraction
A18: F9 | B18: interest_rate | C18: =PlantFinance!B16 -> 0.05 | D18: fraction
A19: CR | B19: counterfactual_spread (AA) | C19: =CreditData!B44 -> 100 | D19: bps
B21: Calculation Step | C21: Result | D21: Unit
B22: Scaled frequency | C22: =C4*C5 -> 0.975 | D22: events/yr
B23: P(outage|event) | C23: =1-EXP(-C6*C7) -> 0.32967995 | D23: probability
B24: Outage rate | C24: =C22*C23*(C8/8760) -> 0.0017613039 | D24: fraction
B25: Hours lost / year | C25: =C24*8760 -> 15.429022 | D25: hours/yr
B27: Annual generation | C27: =C10*C11*8760 -> 11037600 | D27: MWh/yr
B28: Gross revenue | C28: =C27*C12 -> 883008000 | D28: USD/yr
B29: Revenue after physical risk | C29: =C28*(1-C24) -> 8.8145275e+08 | D29: USD/yr
B30: Fuel cost | C30: =C27*C13 -> 496692000 | D30: USD/yr
B31: Fixed O&M | C31: =C14*C10*1000 -> 73500000 | D31: USD/yr
B32: Variable O&M | C32: =C15*C27 -> 49669200 | D32: USD/yr
B33: EBITDA | C33: =C29-C30-C31-C32 -> 2.6159155e+08 | D33: USD/yr
B34: Debt service (interest) | C34: =C16*1000000*C17*C18 -> 142000000 | D34: USD/yr
B35: DSCR | C35: =C33/C34 -> 1.842194 | D35: ratio
B37: Credit Rating | C37: =IF(C35>=2.5,"AAA",IF(C35>=2,"AA",IF(C35>=1.6,"A",IF(C35>=1.3,"BBB",IF(C35>=1.1,"BB","B"))))) -> A | D37: rating
B38: Credit Spread | C38: =IF(C37="AAA",50,IF(C37="AA",100,IF(C37="A",150,IF(C37="BBB",250,IF(C37="BB",400,600))))) -> 150 | D38: bps
B39: Counterfactual (AA) | C39: =C19 -> 100 | D39: bps
B40: CRP (Climate Risk Premium) | C40: =MAX(0,C38-C39) -> 50 | D40: bps
